flnet/__init__.py
flnet-1.2.data/scripts/flnet-dumbbell
flnet-1.2.dist-info/LICENSE
flnet-1.2.dist-info/METADATA
flnet-1.2.dist-info/WHEEL
flnet-1.2.dist-info/top_level.txt
flnet-1.2.dist-info/RECORD
